trame/__init__.py
trame/modules/__init__.py
trame/modules/components.py
trame/widgets/__init__.py
trame/widgets/gwc.py
trame_gwc/__init__.py
trame_gwc/module/__init__.py
trame_gwc/module/serve/trame-gwc.css
trame_gwc/module/serve/trame-gwc.umd.min.js
trame_gwc/module/serve/trame-gwc.umd.min.js.map
trame_gwc/module/serve/fonts/materialdesignicons-webfont.147e3378.woff
trame_gwc/module/serve/fonts/materialdesignicons-webfont.174c02fc.ttf
trame_gwc/module/serve/fonts/materialdesignicons-webfont.64d4cf64.eot
trame_gwc/module/serve/fonts/materialdesignicons-webfont.6a2ddad1.6a2ddad1.ttf
trame_gwc/module/serve/fonts/materialdesignicons-webfont.7a44ea19.woff2
trame_gwc/module/serve/fonts/materialdesignicons-webfont.8a670406.8a670406.eot
trame_gwc/module/serve/fonts/materialdesignicons-webfont.c32505e8.c32505e8.woff
trame_gwc/module/serve/fonts/materialdesignicons-webfont.dc85ceeb.dc85ceeb.woff2
trame_gwc/widgets/__init__.py
trame_gwc/widgets/gwc.py
trame_gwc-0.1.0.dist-info/LICENSE
trame_gwc-0.1.0.dist-info/METADATA
trame_gwc-0.1.0.dist-info/WHEEL
trame_gwc-0.1.0.dist-info/top_level.txt
trame_gwc-0.1.0.dist-info/RECORD
